{"v":"5.5.0","fr":30,"ip":0,"op":60,"w":720,"h":420,"nm":"guacamaya_mov","ddd":0,"assets":[],"layers":[{"ddd":0,"ind":1,"ty":4,"nm":"copete Outlines","parent":5,"sr":1,"ks":{"o":{"a":0,"k":100,"ix":11},"r":{"a":1,"k":[{"i":{"x":[0.667],"y":[1]},"o":{"x":[0.333],"y":[0]},"t":0,"s":[0]},{"i":{"x":[0.667],"y":[1]},"o":{"x":[0.333],"y":[0]},"t":15,"s":[5]},{"i":{"x":[0.667],"y":[1]},"o":{"x":[0.333],"y":[0]},"t":30,"s":[0]},{"i":{"x":[0.667],"y":[1]},"o":{"x":[0.333],"y":[0]},"t":45,"s":[5]},{"t":60,"s":[0]}],"ix":10},"p":{"a":0,"k":[523,56,0],"ix":2},"a":{"a":0,"k":[523,56,0],"ix":1},"s":{"a":0,"k":[100,100,100],"ix":6}},"ao":0,"shapes":[{"ty":"gr","it":[{"ind":0,"ty":"sh","ix":1,"ks":{"a":0,"k":{"i":[[0.39,-1.346],[9.176,2.657],[-0.39,1.346],[-9.177,-2.656]],"o":[[-0.39,1.346],[-9.177,-2.657],[0.389,-1.346],[9.177,2.658]],"v":[[16.616,4.81],[-0.706,2.438],[-16.616,-4.81],[0.706,-2.439]],"c":true},"ix":2},"nm":"Path 1","mn":"ADBE Vector Shape - Group","hd":false},{"ty":"fl","c":{"a":0,"k":[0.877999997606,0.184000007779,0.270999983245,1],"ix":4},"o":{"a":0,"k":100,"ix":5},"r":1,"bm":0,"nm":"Fill 1","mn":"ADBE Vector Graphic - Fill","hd":false},{"ty":"tr","p":{"a":0,"k":[498.156,51.398],"ix":2},"a":{"a":0,"k":[0,0],"ix":1},"s":{"a":0,"k":[100,100],"ix":3},"r":{"a":0,"k":0,"ix":6},"o":{"a":0,"k":100,"ix":7},"sk":{"a":0,"k":0,"ix":4},"sa":{"a":0,"k":0,"ix":5},"nm":"Transform"}],"nm":"Group 1","np":2,"cix":2,"bm":0,"ix":1,"mn":"ADBE Vector Group","hd":false},{"ty":"gr","it":[{"ind":0,"ty":"sh","ix":1,"ks":{"a":0,"k":{"i":[[1.152,-1.455],[9.919,7.855],[-1.152,1.455],[-9.919,-7.855]],"o":[[-1.152,1.455],[-9.919,-7.855],[1.152,-1.455],[9.919,7.855]],"v":[[17.96,14.222],[-2.086,2.635],[-17.959,-14.222],[2.087,-2.635]],"c":true},"ix":2},"nm":"Path 1","mn":"ADBE Vector Shape - Group","hd":false},{"ty":"fl","c":{"a":0,"k":[0.877999997606,0.184000007779,0.270999983245,1],"ix":4},"o":{"a":0,"k":100,"ix":5},"r":1,"bm":0,"nm":"Fill 1","mn":"ADBE Vector Graphic - Fill","hd":false},{"ty":"tr","p":{"a":0,"k":[507.022,41.446],"ix":2},"a":{"a":0,"k":[0,0],"ix":1},"s":{"a":0,"k":[100,100],"ix":3},"r":{"a":0,"k":0,"ix":6},"o":{"a":0,"k":100,"ix":7},"sk":{"a":0,"k":0,"ix":4},"sa":{"a":0,"k":0,"ix":5},"nm":"Transform"}],"nm":"Group 2","np":2,"cix":2,"bm":0,"ix":2,"mn":"ADBE Vector Group","hd":false}],"ip":0,"op":60,"st":0,"bm":0},{"ddd":0,"ind":2,"ty":4,"nm":"plumas Outlines","parent":5,"sr":1,"ks":{"o":{"a":0,"k":100,"ix":11},"r":{"a":1,"k":[{"i":{"x":[0.667],"y":[1]},"o":{"x":[0.333],"y":[0]},"t":0,"s":[0]},{"i":{"x":[0.667],"y":[1]},"o":{"x":[0.333],"y":[0]},"t":15,"s":[-10]},{"i":{"x":[0.667],"y":[1]},"o":{"x":[0.333],"y":[0]},"t":30,"s":[0]},{"i":{"x":[0.667],"y":[1]},"o":{"x":[0.333],"y":[0]},"t":45,"s":[-10]},{"t":60,"s":[0]}],"ix":10},"p":{"a":0,"k":[252,126,0],"ix":2},"a":{"a":0,"k":[252,126,0],"ix":1},"s":{"a":0,"k":[100,100,100],"ix":6}},"ao":0,"shapes":[{"ty":"gr","it":[{"ind":0,"ty":"sh","ix":1,"ks":{"a":0,"k":{"i":[[3.454,-5.449],[51.52,32.662],[-3.455,5.448],[-51.52,-32.663]],"o":[[-3.455,5.449],[-51.519,-32.663],[3.454,-5.449],[51.52,32.662]],"v":[[93.285,59.14],[-6.255,9.865],[-93.284,-59.14],[6.255,-9.865]],"c":true},"ix":2},"nm":"Path 1","mn":"ADBE Vector Shape - Group","hd":false},{"ty":"fl","c":{"a":0,"k":[0.2,0.528999956916,0.757000014361,1],"ix":4},"o":{"a":0,"k":100,"ix":5},"r":1,"bm":0,"nm":"Fill 1","mn":"ADBE Vector Graphic - Fill","hd":false},{"ty":"tr","p":{"a":0,"k":[161.127,66.725],"ix":2},"a":{"a":0,"k":[0,0],"ix":1},"s":{"a":0,"k":[100,100],"ix":3},"r":{"a":0,"k":0,"ix":6},"o":{"a":0,"k":100,"ix":7},"sk":{"a":0,"k":0,"ix":4},"sa":{"a":0,"k":0,"ix":5},"nm":"Transform"}],"nm":"Group 1","np":2,"cix":2,"bm":0,"ix":1,"mn":"ADBE Vector Group","hd":false},{"ty":"gr","it":[{"ind":0,"ty":"sh","ix":1,"ks":{"a":0,"k":{"i":[[1.501,-4.696],[44.399,14.2],[-1.502,4.695],[-44.4,-14.199]],"o":[[-1.501,4.695],[-44.4,-14.198],[1.502,-4.696],[44.399,14.199]],"v":[[80.393,25.71],[-2.718,8.502],[-80.392,-25.709],[2.72,-8.502]],"c":true},"ix":2},"nm":"Path 1","mn":"ADBE Vector Shape - Group","hd":false},{"ty":"fl","c":{"a":0,"k":[0.957000014361,0.709999952129,0.383999992819,1],"ix":4},"o":{"a":0,"k":100,"ix":5},"r":1,"bm":0,"nm":"Fill 1","mn":"ADBE Vector Graphic - Fill","hd":false},{"ty":"tr","p":{"a":0,"k":[174.185,99.862],"ix":2},"a":{"a":0,"k":[0,0],"ix":1},"s":{"a":0,"k":[100,100],"ix":3},"r":{"a":0,"k":0,"ix":6},"o":{"a":0,"k":100,"ix":7},"sk":{"a":0,"k":0,"ix":4},"sa":{"a":0,"k":0,"ix":5},"nm":"Transform"}],"nm":"Group 2","np":2,"cix":2,"bm":0,"ix":2,"mn":"ADBE Vector Group","hd":false},{"ty":"gr","it":[{"ind":0,"ty":"sh","ix":1,"ks":{"a":0,"k":{"i":[[0.109,-3.711],[35.087,1.029],[-0.109,3.711],[-35.087,-1.029]],"o":[[-0.109,3.711],[-35.086,-1.029],[0.109,-3.71],[35.087,1.029]],"v":[[63.531,1.864],[-0.198,6.719],[-63.531,-1.864],[0.197,-6.719]],"c":true},"ix":2},"nm":"Path 1","mn":"ADBE Vector Shape - Group","hd":false},{"ty":"fl","c":{"a":0,"k":[0.877999997606,0.184000007779,0.270999983245,1],"ix":4},"o":{"a":0,"k":100,"ix":5},"r":1,"bm":0,"nm":"Fill 1","mn":"ADBE Vector Graphic - Fill","hd":false},{"ty":"tr","p":{"a":0,"k":[191.093,123.396],"ix":2},"a":{"a":0,"k":[0,0],"ix":1},"s":{"a":0,"k":[100,100],"ix":3},"r":{"a":0,"k":0,"ix":6},"o":{"a":0,"k":100,"ix":7},"sk":{"a":0,"k":0,"ix":4},"sa":{"a":0,"k":0,"ix":5},"nm":"Transform"}],"nm":"Group 3","np":2,"cix":2,"bm":0,"ix":3,"mn":"ADBE Vector Group","hd":false}],"ip":0,"op":60,"st":0,"bm":0},{"ddd":0,"ind":3,"ty":4,"nm":"ojo Outlines","parent":5,"sr":1,"ks":{"o":{"a":0,"k":100,"ix":11},"r":{"a":0,"k":0,"ix":10},"p":{"a":1,"k":[{"i":{"x":0.667,"y":1},"o":{"x":0.333,"y":0},"t":0,"s":[528,109,0],"to":[0,-0.333,0],"ti":[0,0,0]},{"i":{"x":0.667,"y":1},"o":{"x":0.333,"y":0},"t":15,"s":[528,107,0],"to":[0,0,0],"ti":[0,0,0]},{"t":30,"s":[528,109,0]}],"ix":2},"a":{"a":1,"k":[{"i":{"x":0.667,"y":0.667},"o":{"x":0.333,"y":0.333},"t":0,"s":[528,109,0],"to":[0,0,0],"ti":[0,0,0]},{"i":{"x":0.667,"y":0.667},"o":{"x":0.333,"y":0.333},"t":15,"s":[528,109,0],"to":[0,0,0],"ti":[0,0,0]},{"t":30,"s":[528,109,0]}],"ix":1},"s":{"a":1,"k":[{"i":{"x":[0.667,0.667,0.667],"y":[1,1,1]},"o":{"x":[0.333,0.333,0.333],"y":[0,0,0]},"t":5,"s":[100,100,100]},{"i":{"x":[0.667,0.667,0.667],"y":[1,1,1]},"o":{"x":[0.333,0.333,0.333],"y":[0,0,0]},"t":7,"s":[100,5,100]},{"i":{"x":[0.667,0.667,0.667],"y":[1,1,1]},"o":{"x":[0.333,0.333,0.333],"y":[0,0,0]},"t":9,"s":[100,5,100]},{"i":{"x":[0.833,0.833,0.833],"y":[1,1,1]},"o":{"x":[0.167,0.167,0.167],"y":[0,0,0]},"t":11,"s":[100,100,100]},{"i":{"x":[0.667,0.667,0.667],"y":[1,1,1]},"o":{"x":[0.333,0.333,0.333],"y":[0,0,0]},"t":20,"s":[100,100,100]},{"i":{"x":[0.667,0.667,0.667],"y":[1,1,1]},"o":{"x":[0.333,0.333,0.333],"y":[0,0,0]},"t":22,"s":[100,5,100]},{"i":{"x":[0.667,0.667,0.667],"y":[1,1,1]},"o":{"x":[0.333,0.333,0.333],"y":[0,0,0]},"t":24,"s":[100,5,100]},{"t":26,"s":[100,100,100]}],"ix":6}},"ao":0,"shapes":[{"ty":"gr","it":[{"ind":0,"ty":"sh","ix":1,"ks":{"a":0,"k":{"i":[[1.009,1.826],[2.809,0],[0,2.832],[-2.733,0.112],[2.105,0],[0,-7.044],[-7.044,0],[0,7.043]],"o":[[-0.036,2.801],[-2.833,0],[0,-2.762],[-1.75,-0.903],[-7.044,0],[0,7.043],[7.044,0],[0,-2.234]],"v":[[11.167,-6.157],[6.045,-1.094],[0.915,-6.222],[5.836,-11.331],[0,-12.753],[-12.754,0.001],[0,12.753],[12.754,0.001]],"c":true},"ix":2},"nm":"Path 1","mn":"ADBE Vector Shape - Group","hd":false},{"ty":"fl","c":{"a":0,"k":[0.136999990426,0.122000002394,0.125,1],"ix":4},"o":{"a":0,"k":100,"ix":5},"r":1,"bm":0,"nm":"Fill 1","mn":"ADBE Vector Graphic - Fill","hd":false},{"ty":"tr","p":{"a":0,"k":[526.533,107.238],"ix":2},"a":{"a":0,"k":[0,0],"ix":1},"s":{"a":0,"k":[100,100],"ix":3},"r":{"a":0,"k":0,"ix":6},"o":{"a":0,"k":100,"ix":7},"sk":{"a":0,"k":0,"ix":4},"sa":{"a":0,"k":0,"ix":5},"nm":"Transform"}],"nm":"Group 1","np":2,"cix":2,"bm":0,"ix":1,"mn":"ADBE Vector Group","hd":false}],"ip":0,"op":60,"st":0,"bm":0},{"ddd":0,"ind":4,"ty":4,"nm":"pata Outlines","parent":5,"sr":1,"ks":{"o":{"a":0,"k":100,"ix":11},"r":{"a":1,"k":[{"i":{"x":[0.667],"y":[1]},"o":{"x":[0.333],"y":[0]},"t":0,"s":[36]},{"i":{"x":[0.667],"y":[1]},"o":{"x":[0.333],"y":[0]},"t":15,"s":[-121]},{"i":{"x":[0.667],"y":[1]},"o":{"x":[0.333],"y":[0]},"t":30,"s":[36]},{"i":{"x":[0.667],"y":[1]},"o":{"x":[0.333],"y":[0]},"t":45,"s":[-121]},{"t":60,"s":[36]}],"ix":10},"p":{"a":1,"k":[{"i":{"x":0.667,"y":1},"o":{"x":0.333,"y":0},"t":0,"s":[290.758,218.993,0],"to":[0.234,-0.009,0],"ti":[0,0,0]},{"i":{"x":0.667,"y":1},"o":{"x":0.333,"y":0},"t":15,"s":[363.147,213.957,0],"to":[0,0,0],"ti":[-11.331,0.42,0]},{"i":{"x":0.667,"y":1},"o":{"x":0.333,"y":0},"t":30,"s":[290.758,218.993,0],"to":[0.234,-0.009,0],"ti":[0,0,0]},{"i":{"x":0.667,"y":1},"o":{"x":0.333,"y":0},"t":45,"s":[363.147,213.957,0],"to":[0,0,0],"ti":[-11.331,0.42,0]},{"t":60,"s":[290.758,218.993,0]}],"ix":2},"a":{"a":0,"k":[292,229,0],"ix":1},"s":{"a":0,"k":[125.895,125.895,100],"ix":6}},"ao":0,"shapes":[{"ty":"gr","it":[{"ind":0,"ty":"sh","ix":1,"ks":{"a":0,"k":{"i":[[0,0],[8.761,7.003],[0,0]],"o":[[0,0],[-9.33,-7.457],[0,0]],"v":[[15.871,-1.147],[-6.54,9.197],[-1.461,-16.2]],"c":true},"ix":2},"nm":"Path 1","mn":"ADBE Vector Shape - Group","hd":false},{"ty":"fl","c":{"a":0,"k":[0.8,0.105999995213,0.258999992819,1],"ix":4},"o":{"a":0,"k":100,"ix":5},"r":1,"bm":0,"nm":"Fill 1","mn":"ADBE Vector Graphic - Fill","hd":false},{"ty":"tr","p":{"a":0,"k":[285.024,231.75],"ix":2},"a":{"a":0,"k":[0,0],"ix":1},"s":{"a":0,"k":[100,100],"ix":3},"r":{"a":0,"k":-21.616,"ix":6},"o":{"a":0,"k":100,"ix":7},"sk":{"a":0,"k":0,"ix":4},"sa":{"a":0,"k":0,"ix":5},"nm":"Transform"}],"nm":"Group 1","np":2,"cix":2,"bm":0,"ix":1,"mn":"ADBE Vector Group","hd":false},{"ty":"gr","it":[{"ind":0,"ty":"sh","ix":1,"ks":{"a":0,"k":{"i":[[1.383,0.731],[0.737,-1.38],[16.783,-8.167],[5.968,0.535],[-0.878,7.255],[1.555,0.188],[0.189,-1.557],[0.124,-0.166],[0.006,-0.008],[0.006,-0.009],[-1.325,-10.641],[-0.346,-0.46],[-0.861,0],[-0.51,0.383],[0.942,1.253],[1.128,9.054],[-0.645,2.404],[-2.141,-4.437],[-6.254,-4.597],[-0.643,0],[-0.56,0.643],[1.182,1.037],[0.064,0.05],[2.395,4.962],[0.756,2.204],[-3.075,-2.144],[-0.327,-0.055],[-0.164,0],[-0.249,1.37],[1.539,0.284],[7.008,4.89],[3.443,4.768],[-11.515,5.611],[-0.342,0.648]],"o":[[-1.386,-0.721],[-0.075,0.144],[-11.106,5.399],[3.098,-4.724],[0.186,-1.553],[-1.558,-0.205],[-1.106,9.17],[-0.004,0.005],[-0.006,0.008],[-0.515,0.716],[1.311,10.545],[0.56,0.743],[0.594,0],[1.253,-0.943],[-0.078,-0.099],[-0.385,-3.095],[1.118,4.181],[2.802,5.799],[0.53,0.438],[0.79,0],[1.032,-1.181],[-0.061,-0.05],[-5.225,-3.837],[-0.983,-2.035],[2.971,3.593],[8.077,5.639],[0.169,0.029],[1.347,0],[0.278,-1.541],[-0.069,-0.01],[-4.4,-3.066],[6.9,0.488],[18.518,-9.003],[0.729,-1.387]],"v":[[34.139,-35.491],[30.301,-34.316],[10.046,-5.051],[-22.579,-6.961],[-13.867,-27.158],[-16.344,-30.313],[-19.506,-27.835],[-29.844,-6.468],[-29.87,-6.433],[-29.889,-6.406],[-34.727,13.11],[-24.878,35.081],[-22.607,36.212],[-20.902,35.641],[-20.342,31.666],[-29.094,12.411],[-28.447,4.052],[-23.572,17.767],[-10.064,33.335],[-8.247,33.989],[-6.111,33.019],[-6.38,29.01],[-6.973,28.556],[-18.46,15.294],[-21.066,8.834],[-11.685,18.115],[4.54,25.251],[5.042,25.296],[7.83,22.961],[5.544,19.662],[-8.436,13.459],[-21.6,-1.167],[12.53,0.049],[35.322,-31.66]],"c":true},"ix":2},"nm":"Path 1","mn":"ADBE Vector Shape - Group","hd":false},{"ty":"fl","c":{"a":0,"k":[0.136999990426,0.122000002394,0.125,1],"ix":4},"o":{"a":0,"k":100,"ix":5},"r":1,"bm":0,"nm":"Fill 1","mn":"ADBE Vector Graphic - Fill","hd":false},{"ty":"tr","p":{"a":0,"k":[251.118,271.671],"ix":2},"a":{"a":0,"k":[0,0],"ix":1},"s":{"a":0,"k":[100,100],"ix":3},"r":{"a":0,"k":0,"ix":6},"o":{"a":0,"k":100,"ix":7},"sk":{"a":0,"k":0,"ix":4},"sa":{"a":0,"k":0,"ix":5},"nm":"Transform"}],"nm":"Group 2","np":2,"cix":2,"bm":0,"ix":2,"mn":"ADBE Vector Group","hd":false}],"ip":0,"op":60,"st":0,"bm":0},{"ddd":0,"ind":5,"ty":4,"nm":"cuerpo Outlines","sr":1,"ks":{"o":{"a":0,"k":100,"ix":11},"r":{"a":0,"k":0,"ix":10},"p":{"a":1,"k":[{"i":{"x":0.667,"y":1},"o":{"x":0.333,"y":0},"t":0,"s":[361,280.353,0],"to":[0,-1.667,0],"ti":[0,0,0]},{"i":{"x":0.667,"y":1},"o":{"x":0.333,"y":0},"t":8,"s":[361,270.353,0],"to":[0,0,0],"ti":[0,0,0]},{"i":{"x":0.667,"y":1},"o":{"x":0.333,"y":0},"t":15,"s":[361,280.353,0],"to":[0,0,0],"ti":[0,0,0]},{"i":{"x":0.667,"y":1},"o":{"x":0.333,"y":0},"t":23,"s":[361,270.353,0],"to":[0,0,0],"ti":[0,0,0]},{"i":{"x":0.667,"y":1},"o":{"x":0.333,"y":0},"t":30,"s":[361,280.353,0],"to":[0,0,0],"ti":[0,0,0]},{"i":{"x":0.667,"y":1},"o":{"x":0.333,"y":0},"t":38,"s":[361,270.353,0],"to":[0,0,0],"ti":[0,0,0]},{"i":{"x":0.667,"y":1},"o":{"x":0.333,"y":0},"t":45,"s":[361,280.353,0],"to":[0,0,0],"ti":[0,0,0]},{"i":{"x":0.667,"y":1},"o":{"x":0.333,"y":0},"t":53,"s":[361,270.353,0],"to":[0,0,0],"ti":[0,-1.667,0]},{"t":60,"s":[361,280.353,0]}],"ix":2},"a":{"a":0,"k":[360,180,0],"ix":1},"s":{"a":0,"k":[79.431,79.431,100],"ix":6}},"ao":0,"shapes":[{"ty":"gr","it":[{"ind":0,"ty":"sh","ix":1,"ks":{"a":0,"k":{"i":[[22.803,0],[0,-22.804],[-22.804,0],[-1.628,0.195],[-1.034,1.505],[-5.222,14.594],[0,0.125]],"o":[[-22.804,0],[0,22.803],[1.681,0],[5.605,-7.128],[3.13,-4.552],[0,-0.125],[0,-22.804]],"v":[[0,-41.289],[-41.29,0],[0,41.289],[4.955,40.964],[15.033,27.237],[41.271,0.371],[41.289,0]],"c":true},"ix":2},"nm":"Path 1","mn":"ADBE Vector Shape - Group","hd":false},{"ty":"fl","c":{"a":0,"k":[1,1,1,1],"ix":4},"o":{"a":0,"k":100,"ix":5},"r":1,"bm":0,"nm":"Fill 1","mn":"ADBE Vector Graphic - Fill","hd":false},{"ty":"tr","p":{"a":0,"k":[519.141,108.858],"ix":2},"a":{"a":0,"k":[0,0],"ix":1},"s":{"a":0,"k":[100,100],"ix":3},"r":{"a":0,"k":0,"ix":6},"o":{"a":0,"k":100,"ix":7},"sk":{"a":0,"k":0,"ix":4},"sa":{"a":0,"k":0,"ix":5},"nm":"Transform"}],"nm":"Group 1","np":2,"cix":2,"bm":0,"ix":1,"mn":"ADBE Vector Group","hd":false},{"ty":"gr","it":[{"ind":0,"ty":"sh","ix":1,"ks":{"a":0,"k":{"i":[[10.142,-0.471],[5.563,2.473],[4.944,4.943],[2.427,3.56],[0,0],[-0.287,-0.238],[-4.945,-4.943],[-5.563,-2.471],[-7.416,0.078],[-7.238,2.314]],"o":[[-7.408,0.345],[-5.561,-2.471],[-4.724,-4.725],[0,0],[0.492,0.206],[3.708,3.09],[4.944,4.944],[5.562,2.472],[22.664,-0.239],[-10.388,2.07]],"v":[[32.732,11.368],[27.519,-7.314],[-16.391,-7.79],[-14.615,-25.859],[-52.362,-12.579],[-51.154,-11.919],[-52.544,6.621],[-8.634,7.099],[-3.421,25.78],[57.489,7.81]],"c":true},"ix":2},"nm":"Path 1","mn":"ADBE Vector Shape - Group","hd":false},{"ty":"fl","c":{"a":0,"k":[0.2,0.528999956916,0.757000014361,1],"ix":4},"o":{"a":0,"k":100,"ix":5},"r":1,"bm":0,"nm":"Fill 1","mn":"ADBE Vector Graphic - Fill","hd":false},{"ty":"tr","p":{"a":0,"k":[511.949,252.724],"ix":2},"a":{"a":0,"k":[0,0],"ix":1},"s":{"a":0,"k":[100,100],"ix":3},"r":{"a":0,"k":0,"ix":6},"o":{"a":0,"k":100,"ix":7},"sk":{"a":0,"k":0,"ix":4},"sa":{"a":0,"k":0,"ix":5},"nm":"Transform"}],"nm":"Group 2","np":2,"cix":2,"bm":0,"ix":2,"mn":"ADBE Vector Group","hd":false},{"ty":"gr","it":[{"ind":0,"ty":"sh","ix":1,"ks":{"a":0,"k":{"i":[[-10.553,3.746],[0.356,0.296],[6.798,4.945],[3.708,3.364],[5.562,3.708],[3.708,3.09],[6.028,5.608],[3.126,-8.458],[-3.708,-3.09],[-5.561,-3.708],[-3.708,-3.362],[-6.797,-4.943],[-5.483,-2.571]],"o":[[-0.128,-0.421],[-3.708,-3.089],[-6.798,-4.944],[-3.708,-3.362],[-5.562,-3.708],[-3.342,-2.785],[0,0],[-3.127,8.456],[3.708,3.089],[5.563,3.708],[3.708,3.364],[6.38,4.641],[11.631,-3.84]],"v":[[59.905,23.858],[59.225,22.759],[26.626,14.725],[30.67,1.008],[3.141,-7.214],[0.639,-22.622],[-18.764,-36.634],[-56.779,-24.059],[-35.514,-8.21],[-33.013,7.198],[-5.484,15.42],[-9.529,29.136],[22.183,36.634]],"c":true},"ix":2},"nm":"Path 1","mn":"ADBE Vector Shape - Group","hd":false},{"ty":"fl","c":{"a":0,"k":[0.957000014361,0.709999952129,0.383999992819,1],"ix":4},"o":{"a":0,"k":100,"ix":5},"r":1,"bm":0,"nm":"Fill 1","mn":"ADBE Vector Graphic - Fill","hd":false},{"ty":"tr","p":{"a":0,"k":[437.722,203.247],"ix":2},"a":{"a":0,"k":[0,0],"ix":1},"s":{"a":0,"k":[100,100],"ix":3},"r":{"a":0,"k":0,"ix":6},"o":{"a":0,"k":100,"ix":7},"sk":{"a":0,"k":0,"ix":4},"sa":{"a":0,"k":0,"ix":5},"nm":"Transform"}],"nm":"Group 3","np":2,"cix":2,"bm":0,"ix":3,"mn":"ADBE Vector Group","hd":false},{"ty":"gr","it":[{"ind":0,"ty":"sh","ix":1,"ks":{"a":0,"k":{"i":[[0,0],[-11.742,-8.652],[-17.922,-1.854],[0.618,-6.798],[7.416,0],[9.271,2.472],[11.743,5.562],[22.664,-0.239],[5.563,2.471],[4.944,4.945],[3.708,3.09],[6.799,4.943],[3.708,3.363],[5.562,3.708],[3.708,3.091],[5.562,6.18]],"o":[[0,0],[11.742,8.652],[17.922,1.854],[-0.619,6.798],[3.37,6.018],[4.069,5.821],[-7.238,2.313],[-7.416,0.079],[-5.562,-2.473],[-4.944,-4.944],[-3.708,-3.091],[-6.798,-4.944],[-3.708,-3.362],[-5.562,-3.708],[-3.708,-3.09],[0,0]],"v":[[-42.335,-62.792],[-1.546,-51.667],[70.144,-2.844],[122.057,5.189],[109.149,21.824],[94.246,36.708],[65.817,44.742],[4.907,62.712],[-0.306,44.031],[-44.216,43.553],[-42.825,25.013],[-75.426,16.979],[-71.381,3.262],[-98.91,-4.96],[-101.411,-20.368],[-122.676,-36.217]],"c":false},"ix":2},"nm":"Path 1","mn":"ADBE Vector Shape - Group","hd":false},{"ty":"fl","c":{"a":0,"k":[0.877999997606,0.184000007779,0.270999983245,1],"ix":4},"o":{"a":0,"k":100,"ix":5},"r":1,"bm":0,"nm":"Fill 1","mn":"ADBE Vector Graphic - Fill","hd":false},{"ty":"tr","p":{"a":0,"k":[503.62,215.405],"ix":2},"a":{"a":0,"k":[0,0],"ix":1},"s":{"a":0,"k":[100,100],"ix":3},"r":{"a":0,"k":0,"ix":6},"o":{"a":0,"k":100,"ix":7},"sk":{"a":0,"k":0,"ix":4},"sa":{"a":0,"k":0,"ix":5},"nm":"Transform"}],"nm":"Group 4","np":2,"cix":2,"bm":0,"ix":4,"mn":"ADBE Vector Group","hd":false},{"ty":"gr","it":[{"ind":0,"ty":"sh","ix":1,"ks":{"a":0,"k":{"i":[[9.805,-14.119],[5.03,3.492],[-9.804,14.118],[-5.03,-3.492]],"o":[[-9.804,14.118],[-5.03,-3.493],[9.805,-14.119],[5.029,3.493]],"v":[[9.107,6.324],[-17.752,25.564],[-9.107,-6.324],[17.753,-25.564]],"c":true},"ix":2},"nm":"Path 1","mn":"ADBE Vector Shape - Group","hd":false},{"ty":"fl","c":{"a":0,"k":[0.791999966491,0.885999971278,0.917999985639,1],"ix":4},"o":{"a":0,"k":100,"ix":5},"r":1,"bm":0,"nm":"Fill 1","mn":"ADBE Vector Graphic - Fill","hd":false},{"ty":"tr","p":{"a":0,"k":[627.718,178.954],"ix":2},"a":{"a":0,"k":[0,0],"ix":1},"s":{"a":0,"k":[100,100],"ix":3},"r":{"a":0,"k":0,"ix":6},"o":{"a":0,"k":100,"ix":7},"sk":{"a":0,"k":0,"ix":4},"sa":{"a":0,"k":0,"ix":5},"nm":"Transform"}],"nm":"Group 5","np":2,"cix":2,"bm":0,"ix":5,"mn":"ADBE Vector Group","hd":false},{"ty":"gr","it":[{"ind":0,"ty":"sh","ix":1,"ks":{"a":0,"k":{"i":[[0,0],[0,0],[0,0],[0,0]],"o":[[0,0],[0,0],[0,0],[0,0]],"v":[[33.138,-42.057],[27.832,-45.74],[-33.138,42.057],[-27.833,45.74]],"c":true},"ix":2},"nm":"Path 1","mn":"ADBE Vector Shape - Group","hd":false},{"ty":"fl","c":{"a":0,"k":[0.819999964097,0.827000038297,0.830999995213,1],"ix":4},"o":{"a":0,"k":100,"ix":5},"r":1,"bm":0,"nm":"Fill 1","mn":"ADBE Vector Graphic - Fill","hd":false},{"ty":"tr","p":{"a":0,"k":[617.638,199.131],"ix":2},"a":{"a":0,"k":[0,0],"ix":1},"s":{"a":0,"k":[100,100],"ix":3},"r":{"a":0,"k":0,"ix":6},"o":{"a":0,"k":100,"ix":7},"sk":{"a":0,"k":0,"ix":4},"sa":{"a":0,"k":0,"ix":5},"nm":"Transform"}],"nm":"Group 6","np":2,"cix":2,"bm":0,"ix":6,"mn":"ADBE Vector Group","hd":false},{"ty":"gr","it":[{"ind":0,"ty":"sh","ix":1,"ks":{"a":0,"k":{"i":[[9.804,-14.118],[5.029,3.493],[-9.805,14.118],[-5.03,-3.493]],"o":[[-9.805,14.118],[-5.031,-3.492],[9.804,-14.119],[5.03,3.492]],"v":[[9.107,6.324],[-17.752,25.563],[-9.107,-6.324],[17.752,-25.563]],"c":true},"ix":2},"nm":"Path 1","mn":"ADBE Vector Shape - Group","hd":false},{"ty":"fl","c":{"a":0,"k":[0.819999964097,0.827000038297,0.830999995213,1],"ix":4},"o":{"a":0,"k":100,"ix":5},"r":1,"bm":0,"nm":"Fill 1","mn":"ADBE Vector Graphic - Fill","hd":false},{"ty":"tr","p":{"a":0,"k":[633.023,182.638],"ix":2},"a":{"a":0,"k":[0,0],"ix":1},"s":{"a":0,"k":[100,100],"ix":3},"r":{"a":0,"k":0,"ix":6},"o":{"a":0,"k":100,"ix":7},"sk":{"a":0,"k":0,"ix":4},"sa":{"a":0,"k":0,"ix":5},"nm":"Transform"}],"nm":"Group 7","np":2,"cix":2,"bm":0,"ix":7,"mn":"ADBE Vector Group","hd":false},{"ty":"gr","it":[{"ind":0,"ty":"sh","ix":1,"ks":{"a":0,"k":{"i":[[0,0],[3.48,-1.919],[0,0],[30.484,0],[15.94,13.298],[-4.865,-5.21],[-43.273,1.197],[-11.359,16.304]],"o":[[0,0],[-23.64,13.035],[0,0],[-34.228,0],[4.381,14.051],[18.029,19.308],[94.386,-2.61],[0,0]],"v":[[103.592,-43.233],[91.249,-31.121],[-15.236,-6.855],[-59.229,9.124],[-136.69,-10.262],[-120.802,20.684],[-29.967,51.793],[136.69,-49.792]],"c":true},"ix":2},"nm":"Path 1","mn":"ADBE Vector Shape - Group","hd":false},{"ty":"fl","c":{"a":0,"k":[0.8,0.105999995213,0.258999992819,1],"ix":4},"o":{"a":0,"k":100,"ix":5},"r":1,"bm":0,"nm":"Fill 1","mn":"ADBE Vector Graphic - Fill","hd":false},{"ty":"tr","p":{"a":0,"k":[395.888,188.205],"ix":2},"a":{"a":0,"k":[0,0],"ix":1},"s":{"a":0,"k":[100,100],"ix":3},"r":{"a":0,"k":0,"ix":6},"o":{"a":0,"k":100,"ix":7},"sk":{"a":0,"k":0,"ix":4},"sa":{"a":0,"k":0,"ix":5},"nm":"Transform"}],"nm":"Group 8","np":2,"cix":2,"bm":0,"ix":8,"mn":"ADBE Vector Group","hd":false},{"ty":"gr","it":[{"ind":0,"ty":"sh","ix":1,"ks":{"a":0,"k":{"i":[[-77.406,16.223],[-27.233,4.175],[-25.81,-29.54],[5.099,-7.416],[100.581,-2.781],[18.028,19.309]],"o":[[28.204,-5.911],[44.099,-6.762],[35.204,40.29],[-5.098,7.416],[-43.273,1.196],[-15.403,-16.495]],"v":[[-101.188,-47.283],[-8.891,-56.627],[143.39,-69.528],[129.176,-6.031],[-39.078,97.872],[-129.912,66.762]],"c":true},"ix":2},"nm":"Path 1","mn":"ADBE Vector Shape - Group","hd":false},{"ty":"fl","c":{"a":0,"k":[0.877999997606,0.184000007779,0.270999983245,1],"ix":4},"o":{"a":0,"k":100,"ix":5},"r":1,"bm":0,"nm":"Fill 1","mn":"ADBE Vector Graphic - Fill","hd":false},{"ty":"tr","p":{"a":0,"k":[404.998,142.126],"ix":2},"a":{"a":0,"k":[0,0],"ix":1},"s":{"a":0,"k":[100,100],"ix":3},"r":{"a":0,"k":0,"ix":6},"o":{"a":0,"k":100,"ix":7},"sk":{"a":0,"k":0,"ix":4},"sa":{"a":0,"k":0,"ix":5},"nm":"Transform"}],"nm":"Group 9","np":2,"cix":2,"bm":0,"ix":9,"mn":"ADBE Vector Group","hd":false},{"ty":"gr","it":[{"ind":0,"ty":"sh","ix":1,"ks":{"a":0,"k":{"i":[[0,0],[0,0],[2.163,0.025],[2.472,1.324],[-0.927,1.854]],"o":[[2.077,1.092],[0,0],[-2.163,-0.023],[-2.473,-1.325],[0.927,-1.854]],"v":[[-6.208,-40.04],[65.509,19.098],[33.372,40.016],[-25.339,26.486],[-64.583,-4.195]],"c":true},"ix":2},"nm":"Path 1","mn":"ADBE Vector Shape - Group","hd":false},{"ty":"fl","c":{"a":0,"k":[0.8,0.105999995213,0.258999992819,1],"ix":4},"o":{"a":0,"k":100,"ix":5},"r":1,"bm":0,"nm":"Fill 1","mn":"ADBE Vector Graphic - Fill","hd":false},{"ty":"tr","p":{"a":0,"k":[522.124,196.268],"ix":2},"a":{"a":0,"k":[0,0],"ix":1},"s":{"a":0,"k":[100,100],"ix":3},"r":{"a":0,"k":0,"ix":6},"o":{"a":0,"k":100,"ix":7},"sk":{"a":0,"k":0,"ix":4},"sa":{"a":0,"k":0,"ix":5},"nm":"Transform"}],"nm":"Group 10","np":2,"cix":2,"bm":0,"ix":10,"mn":"ADBE Vector Group","hd":false},{"ty":"gr","it":[{"ind":0,"ty":"sh","ix":1,"ks":{"a":0,"k":{"i":[[0,0],[-7.481,-9.017],[-10.726,5.957],[0,0],[0.709,6.462]],"o":[[0,0],[7.48,9.019],[-15.103,-2.389],[0,0],[0,0]],"v":[[-20.556,-5.548],[-9.331,17.454],[20.557,12.166],[0.104,-13.218],[-2.081,-26.472]],"c":true},"ix":2},"nm":"Path 1","mn":"ADBE Vector Shape - Group","hd":false},{"ty":"fl","c":{"a":0,"k":[0.136999990426,0.122000002394,0.125,1],"ix":4},"o":{"a":0,"k":100,"ix":5},"r":1,"bm":0,"nm":"Fill 1","mn":"ADBE Vector Graphic - Fill","hd":false},{"ty":"tr","p":{"a":0,"k":[539.963,146.956],"ix":2},"a":{"a":0,"k":[0,0],"ix":1},"s":{"a":0,"k":[100,100],"ix":3},"r":{"a":0,"k":0,"ix":6},"o":{"a":0,"k":100,"ix":7},"sk":{"a":0,"k":0,"ix":4},"sa":{"a":0,"k":0,"ix":5},"nm":"Transform"}],"nm":"Group 11","np":2,"cix":2,"bm":0,"ix":11,"mn":"ADBE Vector Group","hd":false},{"ty":"gr","it":[{"ind":0,"ty":"sh","ix":1,"ks":{"a":0,"k":{"i":[[8.746,25.776],[6.404,-2.766],[7.962,2.298],[0,0],[1.345,-6.461],[-3.311,-3.992],[-10.727,5.956],[0,0],[-11.491,-6.563],[0,0]],"o":[[-4.68,1.153],[-12.506,5.397],[0,0],[-1.111,4.995],[1.846,4.295],[7.481,9.018],[-15.104,-2.39],[0,0],[10.173,5.811],[0,0]],"v":[[28.206,-25.772],[11.369,-20.085],[-27.274,-21.161],[-33.032,-14.64],[-36.952,3.505],[-29.218,16.755],[0.671,11.467],[-19.782,-13.918],[1.464,-5.876],[6.807,20.725]],"c":true},"ix":2},"nm":"Path 1","mn":"ADBE Vector Shape - Group","hd":false},{"ty":"fl","c":{"a":0,"k":[0.957000014361,0.882000014361,0.344999994016,1],"ix":4},"o":{"a":0,"k":100,"ix":5},"r":1,"bm":0,"nm":"Fill 1","mn":"ADBE Vector Graphic - Fill","hd":false},{"ty":"tr","p":{"a":0,"k":[559.849,147.656],"ix":2},"a":{"a":0,"k":[0,0],"ix":1},"s":{"a":0,"k":[100,100],"ix":3},"r":{"a":0,"k":0,"ix":6},"o":{"a":0,"k":100,"ix":7},"sk":{"a":0,"k":0,"ix":4},"sa":{"a":0,"k":0,"ix":5},"nm":"Transform"}],"nm":"Group 12","np":2,"cix":2,"bm":0,"ix":12,"mn":"ADBE Vector Group","hd":false},{"ty":"gr","it":[{"ind":0,"ty":"sh","ix":1,"ks":{"a":0,"k":{"i":[[0,0],[-6.948,-17.699],[0,0],[10.174,5.811],[0,0],[-15.103,-2.389],[7.48,9.018],[0,0]],"o":[[0,0],[10.375,26.428],[0,0],[-11.49,-6.563],[0,0],[-10.726,5.956],[-7.481,-9.018],[0,0]],"v":[[-3.638,-36.207],[28.925,-16.739],[7.948,31.158],[2.604,4.557],[-18.641,-3.485],[1.812,21.9],[-28.076,27.188],[-39.301,4.188]],"c":true},"ix":2},"nm":"Path 1","mn":"ADBE Vector Shape - Group","hd":false},{"ty":"fl","c":{"a":0,"k":[0.987999949736,0.936999990426,0.486000001197,1],"ix":4},"o":{"a":0,"k":100,"ix":5},"r":1,"bm":0,"nm":"Fill 1","mn":"ADBE Vector Graphic - Fill","hd":false},{"ty":"tr","p":{"a":0,"k":[558.707,137.222],"ix":2},"a":{"a":0,"k":[0,0],"ix":1},"s":{"a":0,"k":[100,100],"ix":3},"r":{"a":0,"k":0,"ix":6},"o":{"a":0,"k":100,"ix":7},"sk":{"a":0,"k":0,"ix":4},"sa":{"a":0,"k":0,"ix":5},"nm":"Transform"}],"nm":"Group 13","np":2,"cix":2,"bm":0,"ix":13,"mn":"ADBE Vector Group","hd":false}],"ip":0,"op":60,"st":0,"bm":0},{"ddd":0,"ind":6,"ty":4,"nm":"pata Outlines","parent":5,"sr":1,"ks":{"o":{"a":0,"k":100,"ix":11},"r":{"a":1,"k":[{"i":{"x":[0.667],"y":[1]},"o":{"x":[0.333],"y":[0]},"t":0,"s":[-30]},{"i":{"x":[0.667],"y":[1]},"o":{"x":[0.333],"y":[0]},"t":15,"s":[131]},{"i":{"x":[0.667],"y":[1]},"o":{"x":[0.333],"y":[0]},"t":30,"s":[-30]},{"i":{"x":[0.667],"y":[1]},"o":{"x":[0.333],"y":[0]},"t":45,"s":[131]},{"t":60,"s":[-30]}],"ix":10},"p":{"a":1,"k":[{"i":{"x":0.667,"y":1},"o":{"x":0.333,"y":0},"t":0,"s":[358.741,216.945,0],"to":[0,-0.935,0],"ti":[0,0,0]},{"i":{"x":0.667,"y":1},"o":{"x":0.333,"y":0},"t":15,"s":[288.24,213.797,0],"to":[0,0,0],"ti":[0,3.147,0]},{"i":{"x":0.667,"y":1},"o":{"x":0.333,"y":0},"t":30,"s":[358.741,216.945,0],"to":[0,-0.935,0],"ti":[0,0,0]},{"i":{"x":0.667,"y":1},"o":{"x":0.333,"y":0},"t":45,"s":[288.24,213.797,0],"to":[0,0,0],"ti":[0,3.147,0]},{"t":60,"s":[358.741,216.945,0]}],"ix":2},"a":{"a":0,"k":[320,233,0],"ix":1},"s":{"a":0,"k":[125.895,125.895,100],"ix":6}},"ao":0,"ef":[{"ty":34,"nm":"Puppet","np":6,"mn":"ADBE FreePin3","ix":1,"en":1,"ef":[{"ty":7,"nm":"Puppet Engine","mn":"ADBE FreePin3 Puppet Engine","ix":1,"v":{"a":0,"k":2,"ix":1}},{"ty":0,"nm":"Mesh Rotation Refinement","mn":"ADBE FreePin3 Auto Rotate Pins","ix":2,"v":{"a":0,"k":20,"ix":2}},{"ty":7,"nm":"On Transparent","mn":"ADBE FreePin3 On Transparent","ix":3,"v":{"a":0,"k":0,"ix":3}},{"ty":30,"nm":"arap","np":3,"mn":"ADBE FreePin3 ARAP Group","ix":4,"en":1,"ef":[{"ty":6,"nm":"Auto-traced Shapes","mn":"ADBE FreePin3 Outlines","ix":1,"v":0},{"ty":1,"nm":"Mesh","np":1,"mn":"ADBE FreePin3 Mesh Group","ix":2,"en":1,"ef":[]}]}]}],"shapes":[{"ty":"gr","it":[{"ind":0,"ty":"sh","ix":1,"ks":{"a":0,"k":{"i":[[0,0],[7.003,-8.761],[0,0]],"o":[[0,0],[-7.456,9.33],[0,0]],"v":[[-1.146,-15.87],[9.197,6.541],[-16.199,1.46]],"c":true},"ix":2},"nm":"Path 1","mn":"ADBE Vector Shape - Group","hd":false},{"ty":"fl","c":{"a":0,"k":[0.8,0.105999995213,0.258999992819,1],"ix":4},"o":{"a":0,"k":100,"ix":5},"r":1,"bm":0,"nm":"Fill 1","mn":"ADBE Vector Graphic - Fill","hd":false},{"ty":"tr","p":{"a":0,"k":[325.139,239.789],"ix":2},"a":{"a":0,"k":[0,0],"ix":1},"s":{"a":0,"k":[100,100],"ix":3},"r":{"a":0,"k":-18.104,"ix":6},"o":{"a":0,"k":100,"ix":7},"sk":{"a":0,"k":0,"ix":4},"sa":{"a":0,"k":0,"ix":5},"nm":"Transform"}],"nm":"Group 1","np":2,"cix":2,"bm":0,"ix":1,"mn":"ADBE Vector Group","hd":false},{"ty":"gr","it":[{"ind":0,"ty":"sh","ix":1,"ks":{"a":0,"k":{"i":[[0.942,1.253],[1.243,-0.936],[9.053,-1.125],[2.395,0.638],[-4.433,2.143],[-4.595,6.259],[1.164,1.02],[1.048,-1.18],[0.05,-0.066],[4.968,-2.395],[2.2,-0.755],[-2.142,3.071],[-0.061,0.327],[1.541,0.277],[0.272,-1.541],[4.929,-7.068],[4.769,-3.442],[5.6,11.515],[0.646,0.344],[0.732,-1.392],[-1.386,-0.732],[-8.201,-16.866],[0.518,-6.014],[7.575,0.487],[0.1,-1.564],[-1.564,-0.1],[-1.467,-1.194],[-0.037,-0.029],[-0.007,-0.005],[-0.01,-0.007],[-0.005,-0.002],[-0.003,-0.002],[-9.003,0],[-1.11,0.139],[-0.461,0.349]],"o":[[-0.948,-1.265],[-0.099,0.079],[-3.106,0.379],[4.18,-1.119],[5.811,-2.8],[0.982,-1.182],[-1.176,-1.015],[-0.05,0.062],[-3.837,5.229],[-2.031,0.981],[3.588,-2.969],[5.638,-8.078],[0.277,-1.542],[-1.518,-0.26],[-0.011,0.066],[-3.065,4.397],[0.466,-6.902],[-8.998,-18.518],[-1.391,-0.725],[-0.732,1.387],[0.141,0.072],[5.343,10.994],[-4.492,-3.094],[-1.622,-0.176],[-0.1,1.563],[8.99,0.576],[0.036,0.03],[0.023,0.019],[0.006,0.005],[0.004,0.003],[0.004,0.003],[0.666,0.482],[1.047,0],[10.545,-1.307],[1.253,-0.943]],"v":[[35.463,21.464],[31.487,20.904],[12.233,29.652],[3.872,29.012],[17.583,24.132],[33.156,10.625],[32.841,6.672],[28.832,6.943],[28.378,7.536],[15.115,19.02],[8.668,21.622],[17.938,12.25],[25.079,-3.978],[22.783,-7.272],[19.49,-4.975],[13.28,9],[-1.34,22.163],[0.185,-9.934],[-31.836,-34.76],[-35.672,-33.574],[-34.486,-29.737],[-4.915,-7.45],[-7.12,22.952],[-26.829,14.943],[-29.845,17.594],[-27.195,20.611],[-6.824,30.258],[-6.715,30.345],[-6.641,30.406],[-6.602,30.435],[-6.59,30.445],[-6.578,30.452],[9.688,35.486],[12.932,35.285],[34.902,25.439]],"c":true},"ix":2},"nm":"Path 1","mn":"ADBE Vector Shape - Group","hd":false},{"ty":"fl","c":{"a":0,"k":[0.136999990426,0.122000002394,0.125,1],"ix":4},"o":{"a":0,"k":100,"ix":5},"r":1,"bm":0,"nm":"Fill 1","mn":"ADBE Vector Graphic - Fill","hd":false},{"ty":"tr","p":{"a":0,"k":[363.583,273.699],"ix":2},"a":{"a":0,"k":[0,0],"ix":1},"s":{"a":0,"k":[100,100],"ix":3},"r":{"a":0,"k":0,"ix":6},"o":{"a":0,"k":100,"ix":7},"sk":{"a":0,"k":0,"ix":4},"sa":{"a":0,"k":0,"ix":5},"nm":"Transform"}],"nm":"Group 2","np":2,"cix":2,"bm":0,"ix":2,"mn":"ADBE Vector Group","hd":false}],"ip":0,"op":60,"st":0,"bm":0},{"ddd":0,"ind":7,"ty":4,"nm":"sombra Outlines","sr":1,"ks":{"o":{"a":0,"k":100,"ix":11},"r":{"a":0,"k":0,"ix":10},"p":{"a":0,"k":[414,399.373,0],"ix":2},"a":{"a":0,"k":[407,322,0],"ix":1},"s":{"a":1,"k":[{"i":{"x":[0.667,0.667,0.667],"y":[1,1,1]},"o":{"x":[0.333,0.333,0.333],"y":[0,0,0]},"t":0,"s":[86.392,86.392,100]},{"i":{"x":[0.667,0.667,0.667],"y":[1,1,1]},"o":{"x":[0.167,0.167,0.167],"y":[0,0,0]},"t":8,"s":[73.339,86.392,100]},{"i":{"x":[0.667,0.667,0.667],"y":[1,1,1]},"o":{"x":[0.333,0.333,0.333],"y":[0,0,0]},"t":15,"s":[86.392,86.392,100]},{"i":{"x":[0.667,0.667,0.667],"y":[1,1,1]},"o":{"x":[0.167,0.167,0.167],"y":[0,0,0]},"t":23,"s":[73.339,86.392,100]},{"i":{"x":[0.667,0.667,0.667],"y":[1,1,1]},"o":{"x":[0.333,0.333,0.333],"y":[0,0,0]},"t":30,"s":[86.392,86.392,100]},{"i":{"x":[0.667,0.667,0.667],"y":[1,1,1]},"o":{"x":[0.167,0.167,0.167],"y":[0,0,0]},"t":38,"s":[73.339,86.392,100]},{"i":{"x":[0.667,0.667,0.667],"y":[1,1,1]},"o":{"x":[0.333,0.333,0.333],"y":[0,0,0]},"t":45,"s":[86.392,86.392,100]},{"i":{"x":[0.667,0.667,0.667],"y":[1,1,1]},"o":{"x":[0.167,0.167,0.167],"y":[0,0,0]},"t":53,"s":[73.339,86.392,100]},{"t":60,"s":[86.392,86.392,100]}],"ix":6}},"ao":0,"shapes":[{"ty":"gr","it":[{"ind":0,"ty":"sh","ix":1,"ks":{"a":0,"k":{"i":[[0,-3.226],[95.253,0],[0,3.227],[-95.253,0]],"o":[[0,3.227],[-95.253,0],[0,-3.226],[95.253,0]],"v":[[172.471,0],[-0.001,5.841],[-172.471,0],[-0.001,-5.84]],"c":true},"ix":2},"nm":"Path 1","mn":"ADBE Vector Shape - Group","hd":false},{"ty":"fl","c":{"a":0,"k":[0.819999964097,0.827000038297,0.830999995213,1],"ix":4},"o":{"a":0,"k":100,"ix":5},"r":1,"bm":0,"nm":"Fill 1","mn":"ADBE Vector Graphic - Fill","hd":false},{"ty":"tr","p":{"a":0,"k":[406.906,320.917],"ix":2},"a":{"a":0,"k":[0,0],"ix":1},"s":{"a":0,"k":[100,100],"ix":3},"r":{"a":0,"k":0,"ix":6},"o":{"a":0,"k":100,"ix":7},"sk":{"a":0,"k":0,"ix":4},"sa":{"a":0,"k":0,"ix":5},"nm":"Transform"}],"nm":"Group 1","np":2,"cix":2,"bm":0,"ix":1,"mn":"ADBE Vector Group","hd":false}],"ip":0,"op":60,"st":0,"bm":0},{"ddd":0,"ind":8,"ty":4,"nm":"piso Outlines","sr":1,"ks":{"o":{"a":1,"k":[{"i":{"x":[0.667],"y":[1]},"o":{"x":[0.333],"y":[0]},"t":0,"s":[50]},{"t":60,"s":[50]}],"ix":11},"r":{"a":0,"k":0,"ix":10},"p":{"a":1,"k":[{"i":{"x":0.667,"y":0.871},"o":{"x":0.333,"y":0},"t":0,"s":[948,226,0],"to":[0,0,0],"ti":[0,0,0]},{"t":60,"s":[-245.098,225.951,0]}],"ix":2},"a":{"a":0,"k":[360,180,0],"ix":1},"s":{"a":0,"k":[100,100,100],"ix":6}},"ao":0,"shapes":[{"ty":"gr","it":[{"ind":0,"ty":"sh","ix":1,"ks":{"a":0,"k":{"i":[[0,-0.963],[14.337,0],[0,0.962],[-14.338,0]],"o":[[0,0.962],[-14.338,0],[0,-0.963],[14.337,0]],"v":[[25.962,0.001],[0,1.742],[-25.962,0.001],[0,-1.742]],"c":true},"ix":2},"nm":"Path 1","mn":"ADBE Vector Shape - Group","hd":false},{"ty":"fl","c":{"a":0,"k":[0.819999964097,0.827000038297,0.830999995213,1],"ix":4},"o":{"a":0,"k":100,"ix":5},"r":1,"bm":0,"nm":"Fill 1","mn":"ADBE Vector Graphic - Fill","hd":false},{"ty":"tr","p":{"a":0,"k":[160.895,329.448],"ix":2},"a":{"a":0,"k":[0,0],"ix":1},"s":{"a":0,"k":[100,100],"ix":3},"r":{"a":0,"k":0,"ix":6},"o":{"a":0,"k":100,"ix":7},"sk":{"a":0,"k":0,"ix":4},"sa":{"a":0,"k":0,"ix":5},"nm":"Transform"}],"nm":"Group 1","np":2,"cix":2,"bm":0,"ix":1,"mn":"ADBE Vector Group","hd":false},{"ty":"gr","it":[{"ind":0,"ty":"sh","ix":1,"ks":{"a":0,"k":{"i":[[0,-0.962],[14.338,0],[0,0.963],[-14.339,0]],"o":[[0,0.963],[-14.339,0],[0,-0.962],[14.338,0]],"v":[[25.961,0],[0,1.742],[-25.962,0],[0,-1.742]],"c":true},"ix":2},"nm":"Path 1","mn":"ADBE Vector Shape - Group","hd":false},{"ty":"fl","c":{"a":0,"k":[0.819999964097,0.827000038297,0.830999995213,1],"ix":4},"o":{"a":0,"k":100,"ix":5},"r":1,"bm":0,"nm":"Fill 1","mn":"ADBE Vector Graphic - Fill","hd":false},{"ty":"tr","p":{"a":0,"k":[399.156,352.66],"ix":2},"a":{"a":0,"k":[0,0],"ix":1},"s":{"a":0,"k":[100,100],"ix":3},"r":{"a":0,"k":0,"ix":6},"o":{"a":0,"k":100,"ix":7},"sk":{"a":0,"k":0,"ix":4},"sa":{"a":0,"k":0,"ix":5},"nm":"Transform"}],"nm":"Group 2","np":2,"cix":2,"bm":0,"ix":2,"mn":"ADBE Vector Group","hd":false},{"ty":"gr","it":[{"ind":0,"ty":"sh","ix":1,"ks":{"a":0,"k":{"i":[[0,-0.962],[14.338,0],[0,0.963],[-14.338,0]],"o":[[0,0.963],[-14.338,0],[0,-0.962],[14.338,0]],"v":[[25.962,-0.001],[0,1.742],[-25.961,-0.001],[0,-1.742]],"c":true},"ix":2},"nm":"Path 1","mn":"ADBE Vector Shape - Group","hd":false},{"ty":"fl","c":{"a":0,"k":[0.819999964097,0.827000038297,0.830999995213,1],"ix":4},"o":{"a":0,"k":100,"ix":5},"r":1,"bm":0,"nm":"Fill 1","mn":"ADBE Vector Graphic - Fill","hd":false},{"ty":"tr","p":{"a":0,"k":[579.376,343.453],"ix":2},"a":{"a":0,"k":[0,0],"ix":1},"s":{"a":0,"k":[100,100],"ix":3},"r":{"a":0,"k":0,"ix":6},"o":{"a":0,"k":100,"ix":7},"sk":{"a":0,"k":0,"ix":4},"sa":{"a":0,"k":0,"ix":5},"nm":"Transform"}],"nm":"Group 3","np":2,"cix":2,"bm":0,"ix":3,"mn":"ADBE Vector Group","hd":false}],"ip":0,"op":60,"st":0,"bm":0},{"ddd":0,"ind":9,"ty":4,"nm":"Shape Layer 1","sr":1,"ks":{"o":{"a":0,"k":100,"ix":11},"r":{"a":0,"k":0,"ix":10},"p":{"a":0,"k":[360,210,0],"ix":2},"a":{"a":0,"k":[0,0,0],"ix":1},"s":{"a":0,"k":[100,100,100],"ix":6}},"ao":0,"shapes":[{"ty":"gr","it":[{"ty":"rc","d":1,"s":{"a":0,"k":[726.297,425.32],"ix":2},"p":{"a":0,"k":[0,0],"ix":3},"r":{"a":0,"k":0,"ix":4},"nm":"Rectangle Path 1","mn":"ADBE Vector Shape - Rect","hd":false},{"ty":"st","c":{"a":0,"k":[1,1,1,1],"ix":3},"o":{"a":0,"k":100,"ix":4},"w":{"a":0,"k":0,"ix":5},"lc":1,"lj":1,"ml":4,"bm":0,"nm":"Stroke 1","mn":"ADBE Vector Graphic - Stroke","hd":false},{"ty":"fl","c":{"a":0,"k":[1,1,1,1],"ix":4},"o":{"a":0,"k":100,"ix":5},"r":1,"bm":0,"nm":"Fill 1","mn":"ADBE Vector Graphic - Fill","hd":false},{"ty":"tr","p":{"a":0,"k":[0.148,-0.34],"ix":2},"a":{"a":0,"k":[0,0],"ix":1},"s":{"a":0,"k":[100,100],"ix":3},"r":{"a":0,"k":0,"ix":6},"o":{"a":0,"k":100,"ix":7},"sk":{"a":0,"k":0,"ix":4},"sa":{"a":0,"k":0,"ix":5},"nm":"Transform"}],"nm":"Rectangle 1","np":3,"cix":2,"bm":0,"ix":1,"mn":"ADBE Vector Group","hd":false}],"ip":0,"op":60,"st":0,"bm":0}],"markers":[]}